haystack_integrations/components/embedders/py.typed
haystack_integrations/components/embedders/nvidia/__init__.py
haystack_integrations/components/embedders/nvidia/document_embedder.py
haystack_integrations/components/embedders/nvidia/text_embedder.py
haystack_integrations/components/embedders/nvidia/truncate.py
haystack_integrations/components/generators/py.typed
haystack_integrations/components/generators/nvidia/__init__.py
haystack_integrations/components/generators/nvidia/generator.py
haystack_integrations/components/generators/nvidia/chat/__init__.py
haystack_integrations/components/generators/nvidia/chat/chat_generator.py
haystack_integrations/components/rankers/nvidia/__init__.py
haystack_integrations/components/rankers/nvidia/py.typed
haystack_integrations/components/rankers/nvidia/ranker.py
haystack_integrations/components/rankers/nvidia/truncate.py
haystack_integrations/utils/py.typed
haystack_integrations/utils/nvidia/__init__.py
haystack_integrations/utils/nvidia/client.py
haystack_integrations/utils/nvidia/models.py
haystack_integrations/utils/nvidia/nim_backend.py
haystack_integrations/utils/nvidia/utils.py
nvidia_haystack-1.0.0.dist-info/METADATA
nvidia_haystack-1.0.0.dist-info/WHEEL
nvidia_haystack-1.0.0.dist-info/licenses/LICENSE.txt
nvidia_haystack-1.0.0.dist-info/RECORD
